langchain_siliconflow/__init__.py
langchain_siliconflow/chat_models.py
langchain_siliconflow/document_loaders.py
langchain_siliconflow/embeddings.py
langchain_siliconflow/py.typed
langchain_siliconflow/retrievers.py
langchain_siliconflow/toolkits.py
langchain_siliconflow/tools.py
langchain_siliconflow/utils.py
langchain_siliconflow/vectorstores.py
langchain_siliconflow-1.0.0.dist-info/METADATA
langchain_siliconflow-1.0.0.dist-info/WHEEL
langchain_siliconflow-1.0.0.dist-info/licenses/LICENSE
langchain_siliconflow-1.0.0.dist-info/RECORD
