Metadata-Version: 2.4
Name: langchain-siliconflow
Version: 1.0.0
Summary: An integration package connecting SiliconFlow and LangChain
Project-URL: Source Code, https://github.com/siliconflow/langchain-siliconflow
Project-URL: Release Notes, https://github.com/siliconflow/langchain-siliconflow/releases
License: MIT
License-File: LICENSE
Requires-Python: <4.0,>=3.10
Requires-Dist: langchain-core<2.0.0,>=1.1.3
Requires-Dist: langchain-openai<2.0.0,>=1.1.1
Requires-Dist: openai<3.0.0,>=2.9.0
